agentnode/__init__.py
agentnode/cli.py
agentnode/agents/base.py
agentnode/agents/runner.py
agentnode/agents/simple_openai_agent.py
agentnode/core/__init__.py
agentnode/core/base_protocol.py
agentnode/core/base_protocol_adapter.py
agentnode/core/client.py
agentnode/core/connector.py
agentnode/core/network.py
agentnode/core/system_commands.py
agentnode/launchers/__init__.py
agentnode/launchers/discovery_connector.py
agentnode/launchers/network_launcher.py
agentnode/launchers/terminal_console.py
agentnode/models/__init__.py
agentnode/models/manifest.py
agentnode/models/message_thread.py
agentnode/models/messages.py
agentnode/models/network_config.py
agentnode/models/network_profile.py
agentnode/models/tool.py
agentnode/protocols/__init__.py
agentnode/protocols/communication/__init__.py
agentnode/protocols/communication/simple_messaging/__init__.py
agentnode/protocols/communication/simple_messaging/adapter.py
agentnode/protocols/communication/simple_messaging/protocol.py
agentnode/protocols/discovery/__init__.py
agentnode/protocols/discovery/agent_discovery/__init__.py
agentnode/protocols/discovery/agent_discovery/adapter.py
agentnode/protocols/discovery/agent_discovery/protocol.py
agentnode/utils/__init__.py
agentnode/utils/message_util.py
agentnode/utils/network_discovey.py
agentnode/utils/protocol_loaders.py
agentnode-0.4.0.dist-info/licenses/LICENSE
agentnode-0.4.0.dist-info/METADATA
agentnode-0.4.0.dist-info/WHEEL
agentnode-0.4.0.dist-info/entry_points.txt
agentnode-0.4.0.dist-info/top_level.txt
agentnode-0.4.0.dist-info/RECORD
